revChatGPT/V1.py
revChatGPT/V3.py
revChatGPT/__init__.py
revChatGPT/__main__.py
revChatGPT/typings.py
revChatGPT/utils.py
revChatGPT/version.py
revChatGPT/config/enable_internet.json
revChatGPT-6.8.6.dist-info/LICENSE
revChatGPT-6.8.6.dist-info/METADATA
revChatGPT-6.8.6.dist-info/WHEEL
revChatGPT-6.8.6.dist-info/top_level.txt
revChatGPT-6.8.6.dist-info/RECORD
